Workbook

Sheet Pendientes
A1: Pendientes del proyecto
A2: Lista viva. Claude la revisa y te la recuerda en cada sesión hasta que cada ítem pase a Hecho.
A4: # | B4: Pendiente | C4: Quién | D4: Para cuándo | E4: Estado
A5: 1 | B5: Subir el index.html nuevo (marca T de cierre, eslogan, foto con el nombre Alejandro-firma.png) y verificarlo en el celular | C5: Alejandro | D5: Hoy 12 oct | E5: Pendiente
A6: 2 | B6: Verificar que se vea tu foto circular en las firmas y en Quién | C6: Alejandro | D6: Hoy 12 oct | E6: Pendiente
A7: 3 | B7: Magda: la carpeta Magda no tiene FotoMagda3.jpg (Magda con los oficiales); subirla o decir qué foto va ahí | C7: Alejandro | D7: Hoy 12 oct | E7: Pendiente
A8: 4 | B8: GA4: aplicar los 4 ajustes (apagar "cambios de página según el historial", registrar dimensiones, marcar eventos clave, retención de 14 meses) | C8: Alejandro | D8: Hoy 12 oct | E8: Pendiente
A9: 5 | B9: Confirmar los 5 sujetos y horarios del retesteo (13 a 15 oct) | C9: Alejandro | D9: Hoy 12 oct | E9: Pendiente
A10: 6 | B10: Audio: recortar de tu grabación el clip de la gobernadora (30 a 40 s) y subirlo como audio/gobernadora.mp3 | C10: Alejandro | D10: Antes de la 1ª sesión | E10: Pendiente
A11: 7 | B11: Etiquetar la versión del Chocó en GitHub (Releases) antes de la primera sesión | C11: Alejandro | D11: Hoy 12 oct | E11: Pendiente
A12: 8 | B12: Retesteo del Chocó con 5 sujetos (mismas preguntas P0 a P9 más bloque B al final) | C12: Alejandro | D12: 13 a 15 oct | E12: Pendiente
A13: 9 | B13: Bloque B del protocolo y encuesta post-lectura: Claude los redacta | C13: Claude | D13: Martes 13 oct | E13: Pendiente
A14: 10 | B14: Revisar con El Espectador los derechos de reutilizar los textos | C14: Alejandro | D14: Esta semana | E14: Pendiente
A15: 11 | B15: Audios de apertura (choco, aviturismo, magda), cuando tengas dónde grabarlos | C15: Alejandro | D15: Más adelante | E15: Pendiente
A16: 12 | B16: Verificar cifras dudosas del aviturismo: 62,8 millones de dólares vs 3 millones de viajes, 1.963 avistamientos del Global Big Day, 102 reportes 2021-2024, atribución de las 139 amenazadas, Ley 2373 de 2024 | C16: Alejandro | D16: Antes de difundir | E16: Pendiente
... A30: 26 | B30: Fotos de Magda aparecen y portadas del aviturismo con nombres en minúscula (foto1, foto2) | C30: Alejandro | D30: 12 oct | E30: Hecho
A32: Pendientes abiertos | D32: =COUNTIF(E5:E30,"<>Hecho")-COUNTBLANK(E5:E30) -> 21

Sheet Avance
A1: Avance del proyecto (estimación al 12 de octubre de 2026)
A2: Los pesos y los porcentajes son una estimación de Claude: edita las celdas amarillas y el total se recalcula. Lectura clave: el producto va mucho más adelantado que la evidencia.
A4: Componente | B4: Peso | C4: Avance | D4: Aporte | E4: Qué hay hecho | F4: Qué falta
A5: Marco, problema y diagnóstico (encuesta N = 306) | B5: 0.1 | C5: 0.9 | D5: =B5*C5 -> 0.09 | E5: Problema, objetivos, hipótesis H1 a H3 y diagnóstico con la encuesta | F5: Integrarlo en el documento final
A6: Benchmarking y propuesta de valor | B6: 0.08 | C6: 0.85 | D6: =B6*C6 -> 0.068 | E6: Tabla de referentes y hoja "Benchmark aplicado" | F6: Aplicar 3 ítems más y citarlos en el texto
A7: Producto mínimo viable (sitio y 3 piezas) | B7: 0.22 | C7: 0.8 | D7: =B7*C7 -> 0.176 | E7: Sitio, 3 piezas con promesa, interactivos, glosario, capítulos, continuar leyendo, analítica, fotos y gráficos | F7: Audios; newsletter piloto; pulir con lo que muestre el retesteo
A8: Validación con usuarios (línea de base, retesteo, segundo método, analítica) | B8: 0.25 | C8: 0.25 | D8: =B8*C8 -> 0.0625 | E8: Línea de base con 5 sujetos; GA4 recién activo | F8: Retesteo; encuesta; 4 semanas de GA4
A9: KPIs, informe de desempeño y decisión | B9: 0.1 | C9: 0.4 | D9: =B9*C9 -> 0.04 | E9: KPIs definidos, libro de Excel e informe borrador | F9: Datos del retesteo y de GA4; decisión de continuar, ajustar o pivotar
A10: Monetización validada | B10: 0.12 | C10: 0.2 | D10: =B10*C10 -> 0.024 | E10: Hipótesis, benchmark y apuntes de precio | F10: Preventa del taller, precio probado, newsletter piloto
A11: Documento final de tesis | B11: 0.08 | C11: 0.15 | D11: =B11*C11 -> 0.012 | E11: Partes de problema y metodología | F11: Resultados, decisiones y conclusiones
A12: Sustentación | B12: 0.05 | C12: 0 | D12: =B12*C12 -> 0 | E12: — | F12: Guion, demostración y preguntas difíciles
A13: Total | B13: =SUM(B5:B12) -> 1 | D13: =SUMPRODUCT(B5:B12,C5:C12)/SUM(B5:B12) -> 0.4725
A15: Producto (promedio de lo construido) | C15: =C7 -> 0.8
A16: Evidencia (validación con usuarios) | C16: =C8 -> 0.25
A17: Diferencia entre producto y evidencia | C17: =C15-C16 -> 0.55

Sheet KPIs
A1: Trasfondo · KPIs y estado frente a las metas
A2: Línea de base y meta provienen del backlog (historias US01–US10). "Meta propuesta" indica un supuesto mío que debes confirmar. Con n = 5, el semáforo orienta la iteración; no es inferencia estadística.
A4: ID | B4: KPI | C4: Historia / hipótesis | D4: Qué mide (definición operativa) | E4: Instrumento | F4: Línea de base | G4: Meta | H4: Último dato (retesteo) | I4: Estado | J4: Origen de la meta | K4: Lectura | M4: KPI | N4: Línea de base | O4: Meta
A5: K1 | B5: Atención sostenida en el primer tercio | C5: US01 · US05 | D5: Sujetos (de 5) que no pierden atención en el primer tercio del artículo | E5: Observación directa + diario de campo | F5: ='Línea de base'!D12 -> 2 | G5: 4 | H5: ='Retesteo (Sprint 1)'!D13 | I5: =IF(H5="","Sin dato",IF(H5>=G5,"Cumple",IF(F5="","En curso",IF(H5>F5,"Mejora","Sin mejora")))) -> Sin dato | J5: Backlog US01 | M5: K1 Atención | N5: =F5 -> 2 | O5: =G5 -> 4
A6: K2 | B6: Marco prometido articulado con claridad | C6: US02 · H1 | D6: Sujetos que, en P3, articulan el aprendizaje prometido con claridad | E6: Entrevista (P3) | F6: ='Línea de base'!D14 -> 2 | G6: 4 | H6: ='Retesteo (Sprint 1)'!D15 | I6: =IF(H6="","Sin dato",IF(H6>=G6,"Cumple",IF(F6="","En curso",IF(H6>F6,"Mejora","Sin mejora")))) -> Sin dato | J6: Backlog US02 | M6: K2 Marco claro | N6: =F6 -> 2 | O6: =G6 -> 4
A7: K3 | B7: Uso espontáneo del audio | C7: US03 · H1 | D7: Sujetos que activan el audio sin que se les pida | E7: Observación + evento audio_play (GA4) | F7: ='Línea de base'!D13 -> 1 | G7: 3 | H7: ='Retesteo (Sprint 1)'!D14 | I7: =IF(H7="","Sin dato",IF(H7>=G7,"Cumple",IF(F7="","En curso",IF(H7>F7,"Mejora","Sin mejora")))) -> Sin dato | J7: Backlog US03 | M7: K3 Audio | N7: =F7 -> 1 | O7: =G7 -> 3
A8: K4 | B8: Participación en el punto de decisión | C8: US04 | D8: Sujetos que interactúan con el interactivo (conducta observada) | E8: Observación + eventos ix_abrir / ix_elige | G8: 5 | H8: ='Retesteo (Sprint 1)'!D16 | I8: =IF(H8="","Sin dato",IF(H8>=G8,"Cumple",IF(F8="","En curso",IF(H8>F8,"Mejora","Sin mejora")))) -> Sin dato | J8: Meta propuesta (todos los sujetos) | K8: No existía en la línea de base | M8: K5 P9 | N8: =F9 -> 5 | O8: =G9 -> 4
A9: K5 | B9: Interactividad valorada (P9) | C9: US04 | D9: Sujetos con respuesta positiva sobre la interactividad en P9 | E9: Entrevista (P9) | F9: ='Línea de base'!D15 -> 5 | G9: 4 | H9: ='Retesteo (Sprint 1)'!D17 | I9: =IF(H9="","Sin dato",IF(H9>=G9,"Cumple",IF(F9="","En curso",IF(H9>F9,"Mejora","Sin mejora")))) -> Sin dato | J9: Backlog US04 | M9: K7 Pago multimedia | N9: =F11 -> 1.5 | O9: =G11 -> 3
A10: K6 | B10: Primera interrupción voluntaria > 7 min | C10: US05 | D10: Sujetos cuya primera interrupción ocurre después de 7 minutos | E10: Observación cronometrada | G10: 4 | H10: ='Retesteo (Sprint 1)'!D18 | I10: =IF(H10="","Sin dato",IF(H10>=G10,"Cumple",IF(F10="","En curso",IF(H10>F10,"Mejora","Sin mejora")))) -> Sin dato | J10: Backlog US05 | K10: Línea de base variable, sin dato único
A11: K7 | B11: Disposición de pago con multimedia | C11: US06 · H2 | D11: Sujetos que pagarían si hay elementos multimedia (sí declarado) | E11: Entrevista (P7) | F11: 1.5 | G11: 3 | H11: ='Retesteo (Sprint 1)'!D19 | I11: =IF(H11="","Sin dato",IF(H11>=G11,"Cumple",IF(F11="","En curso",IF(H11>F11,"Mejora","Sin mejora")))) -> Sin dato | J11: Backlog US06 | K11: Línea de base tal como figura en el backlog (1,5 de 5)
A12: K8 | B12: Disposición de pago por taller | C12: US09 | D12: Sujetos que declaran que pagarían por un taller | E12: Entrevista | G12: 2 | H12: ='Retesteo (Sprint 1)'!D20 | I12: =IF(H12="","Sin dato",IF(H12>=G12,"Cumple",IF(F12="","En curso",IF(H12>F12,"Mejora","Sin mejora")))) -> Sin dato | J12: Backlog US09 | K12: En la línea de base, 2 sujetos lo mencionaron con condiciones
A13: K9 | B13: Compartir efectivo del enlace | C13: US10 · H3 | D13: Sujetos que comparten el enlace a los 7 días | E13: Seguimiento + evento compartir (GA4) | G13: 2 | H13: ='Retesteo (Sprint 1)'!D21 | I13: =IF(H13="","Sin dato",IF(H13>=G13,"Cumple",IF(F13="","En curso",IF(H13>F13,"Mejora","Sin mejora")))) -> Sin dato | J13: Meta propuesta | K13: En la línea de base, 5 de 5 nombraron a quién compartirían (intención)
A15: Leyenda
A16: Metas en amarillo: editables. "Último dato" se llena solo cuando captures los sujetos en la hoja "Retesteo (Sprint 1)". La línea de base de K7 (1,5) viene del backlog y no se calcula desde la hoja de línea de base.

Sheet Línea de base
A1: Línea de base · artículo del Chocó, versión original (sesiones de septiembre)
A2: Datos de las 5 sesiones de observación individuales. Los sujetos van codificados (S1–S5) por privacidad. Fuente: diario de campo y análisis de patrones de la línea de base; "s/d" = sin dato registrado.
A4: Sujeto | B4: ¿Perdió atención en el primer tercio? | C4: ¿Usó el audio? | D4: Respuesta a P3 (marco prometido) | E4: P9 · gamificación | F4: Disposición de pago (resumen) | G4: ¿Nombró a alguien para compartir? | H4: Tiempo de lectura (mm:ss)
A5: S1 | B5: No | C5: Sí | D5: No articuló | E5: Positiva | F5: s/d | G5: Sí | H5: s/d
A6: S2 | B6: Sí | C6: No | D6: Emocional | E6: Positiva | F6: Condicionada a elementos multimedia (voz de la fuente, cápsulas visuales) | G6: Sí | H6: 11:48
A7: S3 | B7: Sí | C7: No | D7: Clara | E7: Positiva | F7: No pagaría sin una línea editorial que lo convenza antes del artículo | G7: Sí | H7: s/d
A8: S4 | B8: Sí | C8: No | D8: Parcial | E8: Positiva | F8: Disposición 3,5 en la escala del protocolo | G8: Sí | H8: s/d
A9: S5 | B9: No | C9: No | D9: Clara | E9: Positiva | F9: Pagaría a precio moderado | G9: Sí | H9: 14:55
A11: Conteos (fórmulas)
A12: Sujetos que NO perdieron atención | D12: =COUNTIF(B5:B9,"No") -> 2
A13: Sujetos que usaron el audio | D13: =COUNTIF(C5:C9,"Sí") -> 1
A14: Sujetos con marco articulado con claridad (P3) | D14: =COUNTIF(D5:D9,"Clara") -> 2
A15: Sujetos con P9 positiva | D15: =COUNTIF(E5:E9,"Positiva") -> 5
A16: Sujetos que nombraron a alguien para compartir | D16: =COUNTIF(G5:G9,"Sí") -> 5
A18: Nota: la clasificación de P3 como "Clara" sigue el criterio del backlog (US02): solo 2 de 5 lo articularon con claridad. El tiempo de lectura se transcribe tal como figura en el diario de campo.

Sheet Retesteo (Sprint 1)
A1: Sprint 1 · Retesteo del artículo del Chocó (versión con intervenciones)
A2: Celdas amarillas = para llenar. Una fila por sujeto. La fila gris es solo un ejemplo del formato; no entra en los conteos. Las listas desplegables evitan errores de escritura.
A4: Sujeto | B4: Fecha | C4: ¿Perdió atención en el primer tercio? | D4: ¿Usó el audio? | E4: P3 (marco prometido) | F4: ¿Interactuó en el punto de decisión? | G4: P9 · gamificación | H4: Tiempo hasta 1ª interrupción (min) | I4: ¿Pagaría con multimedia? | J4: ¿Pagaría por un taller? | K4: ¿Compartió el enlace (a los 7 días)?
A5: Ejemplo | B5: 2026-10-13 | C5: No | D5: Sí | E5: Clara | F5: Sí | G5: Positiva | H5: 9 | I5: Sí | J5: No | K5: Sí
A6: S1
A7: S2
A8: S3
A9: S4
A10: S5
A12: Conteos (fórmulas)
A13: Sujetos que NO perdieron atención | D13: =IF(COUNTA(C6:C10)=0,"",COUNTIF(C6:C10,"No"))
A14: Sujetos que usaron el audio | D14: =IF(COUNTA(D6:D10)=0,"",COUNTIF(D6:D10,"Sí"))
A15: Sujetos con marco articulado con claridad (P3) | D15: =IF(COUNTA(E6:E10)=0,"",COUNTIF(E6:E10,"Clara"))
A16: Sujetos que interactuaron en el punto de decisión | D16: =IF(COUNTA(F6:F10)=0,"",COUNTIF(F6:F10,"Sí"))
A17: Sujetos con P9 positiva | D17: =IF(COUNTA(G6:G10)=0,"",COUNTIF(G6:G10,"Positiva"))
A18: Sujetos con 1ª interrupción > 7 min | D18: =IF(COUNT(H6:H10)=0,"",COUNTIF(H6:H10,">7"))
A19: Sujetos que pagarían con multimedia (Sí) | D19: =IF(COUNTA(I6:I10)=0,"",COUNTIF(I6:I10,"Sí"))
A20: Sujetos que pagarían por taller | D20: =IF(COUNTA(J6:J10)=0,"",COUNTIF(J6:J10,"Sí"))
A21: Sujetos que compartieron el enlace | D21: =IF(COUNTA(K6:K10)=0,"",COUNTIF(K6:K10,"Sí"))

Sheet Analítica GA4
A1: Analítica del sitio (Google Analytics 4) · Sprint 2
A2: Pega cada semana los conteos de GA4 (Informes > Eventos). Celdas amarillas = entrada; las tasas se calculan solas. La fila gris es un ejemplo del formato (cifras inventadas, no cuentan).
A4: Semana (lunes) | B4: Usuarios | C4: Vistas del Chocó | D4: lectura_avance 25% | E4: lectura_avance 50% | F4: lectura_avance 75% | G4: lectura_avance 100% | H4: ix_abrir | I4: ix_elige | J4: audio_play | K4: compartir | L4: newsletter_submit | M4: Tasa 50 % | N4: Tasa lectura completa
A5: Ejemplo | B5: 40 | C5: 30 | D5: 24 | E5: 18 | F5: 13 | G5: 9 | H5: 12 | I5: 11 | J5: 3 | K5: 2 | L5: 2 | M5: =IF(C5=0,"",E5/C5) -> 0.6 | N5: =IF(C5=0,"",G5/C5) -> 0.3
M6: =IF(N(C6)=0,"",E6/C6) | N6: =IF(N(C6)=0,"",G6/C6)
M7: =IF(N(C7)=0,"",E7/C7) | N7: =IF(N(C7)=0,"",G7/C7)
M8: =IF(N(C8)=0,"",E8/C8) | N8: =IF(N(C8)=0,"",G8/C8)
M9: =IF(N(C9)=0,"",E9/C9) | N9: =IF(N(C9)=0,"",G9/C9)
M10: =IF(N(C10)=0,"",E10/C10) | N10: =IF(N(C10)=0,"",G10/C10)
M11: =IF(N(C11)=0,"",E11/C11) | N11: =IF(N(C11)=0,"",G11/C11)
M12: =IF(N(C12)=0,"",E12/C12) | N12: =IF(N(C12)=0,"",G12/C12)
M13: =IF(N(C13)=0,"",E13/C13) | N13: =IF(N(C13)=0,"",G13/C13)
M14: =IF(N(C14)=0,"",E14/C14) | N14: =IF(N(C14)=0,"",G14/C14)
M15: =IF(N(C15)=0,"",E15/C15) | N15: =IF(N(C15)=0,"",G15/C15)
M16: =IF(N(C16)=0,"",E16/C16) | N16: =IF(N(C16)=0,"",G16/C16)
M17: =IF(N(C17)=0,"",E17/C17) | N17: =IF(N(C17)=0,"",G17/C17)
A19: Cómo se alimenta
A20: Eventos que envía el sitio: page_view (por pieza y por ruta), lectura_avance (hito 25/50/75/100), ix_abrir, ix_elige, audio_play, compartir, newsletter_submit, tema_cambio. Para ver los parámetros (pieza, hito, interactivo, opcion) en los informes, regístralos en GA4 como dimensiones personalizadas de evento.
A21: Metas de analítica: aún sin definir. Propuesta: medir 4 semanas de tráfico real y fijar metas a partir de esa línea de base.

Sheet Substack previo
A1: Substack, canal previo a GitHub · cifras del panel
A2: Datos tal como los entregó el panel de Substack de Trasfondo (antes de pasar al sitio propio). Celdas azules = datos del panel; las negras se calculan. Son cifras de una muestra mínima: sirven de referencia, no de conclusión.
A4: Dato del perfil | B4: Valor
A5: Suscriptores totales | B5: 6
A6: Vistas totales (perfil) | B6: 95
A7: Nuevos suscriptores | B7: —
A8: Tasa de apertura (perfil) | B8: 0.5
A9: Última publicación | B9: 18 sept (Chocó)
A11: Pieza | B11: Publicada | C11: Visitas | D11: Destinatarios | E11: Aperturas | F11: Tasa de apertura | G11: Clics en enlaces | H11: Me gusta | I11: Comentarios | J11: Fuente: directo | K11: Fuente: direct-to-app | L11: Fuente: app Substack | M11: Dispositivo: escritorio | N11: Dispositivo: web móvil | O11: Dispositivo: app Substack | P11: Móvil total (web + app) | Q11: Visitas por destinatario
A12: Un vuelo humanitario para un Chocó… | B12: 18 sept | C12: 26 | D12: 4 | E12: 2 | F12: =IF(D12=0,"",E12/D12) -> 0.5 | G12: 0 | H12: 0 | I12: 0 | J12: 0.81 | K12: 0.15 | L12: 0.04 | M12: 0.62 | N12: 0.23 | O12: 0.15 | P12: =N12+O12 -> 0.38 | Q12: =IF(D12=0,"",C12/D12) -> 6.5
A13: Del boom del aviturismo a la alerta… | B13: 26 ago | C13: 23 | D13: 2 | E13: 1 | F13: =IF(D13=0,"",E13/D13) -> 0.5 | G13: 0 | H13: 1 | I13: 0 | J13: 0.74 | K13: 0.13 | L13: 0.13 | M13: 0.43 | N13: 0.04 | O13: 0.52 | P13: =N13+O13 -> 0.56 | Q13: =IF(D13=0,"",C13/D13) -> 11.5
A15: Lectura crítica
A16: 1. Muestra mínima: 4 y 2 destinatarios. Una apertura más o menos mueve la tasa 25 o 50 puntos, y las visitas no distinguen lectores únicos ni excluyen las del propio autor.
A17: 2. Móvil: en el Chocó solo el 38 % de las visitas fue móvil (web + app) y el 62 % fue de escritorio; en aviturismo fue el 56 %. Tu encuesta (N = 306) dice que el 60 % lee en celular: el canal previo no confirma ni desmiente el supuesto móvil. Hay que verificarlo con GA4.
A18: 3. Ningún enlace recibió clics y la profundidad de lectura figura como "aún no hay suficientes lectores": Substack no sirve para medir lectura. Es la razón práctica para medir con GA4.
A19: 4. Esto es la línea de base de distribución (apertura, visitas, suscriptores), no de comprensión. La comprensión se mide en las sesiones con sujetos.

Sheet Decisiones
A1: Regla de decisión: continuar, ajustar o pivotar
A2: Los umbrales son una propuesta (celdas amarillas, editables). Para el profesor, la decisión final combina esta señal con el análisis cualitativo.
A4: KPIs que cumplen la meta | C4: =COUNTIF(KPIs!I5:I13,"Cumple") -> 0
A5: KPIs con dato registrado | C5: =SUMPRODUCT(--(KPIs!H5:H13<>"")) -> 0
A6: Umbral para CONTINUAR (≥) | C6: 6 | E6: Supuesto: 6 de 9 KPIs en meta = continuar; 3 a 5 = ajustar; menos de 3 = evaluar pivote. Proponlo al profesor y cámbialo si hace falta.
A7: Umbral para AJUSTAR (≥) | C7: 3
A8: Señal actual | C8: =IF(C5=0,"Sin datos del retesteo",IF(C4>=C6,"CONTINUAR",IF(C4>=C7,"AJUSTAR","REVISAR PIVOTE"))) -> Sin datos del retesteo
A10: Registro de decisiones
A11: Fecha | B11: Dato / KPI que la motiva | C11: Interpretación | D11: Decisión (continuar / ajustar / pivotar) | E11: Acción concreta | F11: Responsable | G11: Cuándo se revisa
A12: Ejemplo | B12: K1 pasó de 2 a 4 de 5 | C12: El ancla del primer tercio redujo la pérdida de atención | D12: Continuar | E12: Aplicar el ancla a las demás piezas | F12: Alejandro | G12: Sprint 3

Sheet Benchmark aplicado
A1: Benchmarking aplicado: qué rescatar de cada referente
A2: "Qué hacen bien" resume tu tabla del segundo semestre (Big Think no estaba en ella: lo añadí tras revisar su portada). La columna de aplicación son propuestas mías; el estado se cambia con el desplegable.
A4: Referente | B4: Qué hacen bien | C4: Qué rescatar | D4: Aplicación concreta en Trasfondo | E4: Estado | F4: Dónde
A5: Cerosetenta | B5: Puentes entre rigor académico y narrativa; enfoque en comprensión; nativo digital colombiano | C5: Alianza con la universidad como respaldo y canal | D5: Kit docente: pieza + guía de discusión + audio, para cursos de periodismo | E5: Propuesto | F5: Monetización (línea 2)
A6: DianaUribe.fm | B6: Podcast narrativo de largo aliento; comunidad en Patreon; marca personal; sitio propio | C6: El audio como producto central y la comunidad que paga | D6: Audio de apertura por pieza (hecho); membresía de comunidad cuando haya audiencia | E6: Aplicado en parte | F6: Bloque de audio en cada pieza
A7: Vorágine | B7: Cada periodista cuenta en redes, de forma clara y fresca, de qué trata la investigación | C7: Anunciar la promesa antes del enlace | D7: Mensaje corto en WhatsApp con el "qué vas a entender" de la pieza | E7: Propuesto | F7: Difusión por WhatsApp
A8: El Malpensante | B8: Propuesta visual sólida y dirección de arte arriesgada | C8: Identidad visual como parte del valor | D8: Tipografía Fraunces + Alegreya (hecho); ilustración o fotografía propia por pieza | E8: Aplicado en parte | F8: Sistema visual
A9: Radio Ambulante | B9: Series temáticas, clubes de escucha, alianzas, membresía | C9: Comunidad alrededor de cada serie | D9: Clubes de lectura mensuales ligados al taller | E9: Propuesto | F9: Taller
A10: Zetland | B10: "Hace sentido, no hace noticias"; texto y audio; eventos en vivo; 50 % de suscriptores menores de 35 | C10: Texto + audio juntos y el evento en vivo | D10: Audio junto al texto (hecho); evento o taller en vivo por Número | E10: Aplicado en parte | F10: Audio y taller
A11: The Continent | B11: Mobile first, distribución directa por WhatsApp, formato para compartir, periodicidad definida, concisión | C11: Que el formato mismo invite a compartirse | D11: Botón compartir (hecho); tarjeta descargable de la promesa para el estado de WhatsApp; fecha fija de salida | E11: Aplicado en parte | F11: Compartir y newsletter
A12: Aos Fatos | B12: Audiencia joven latinoamericana que paga por rigor independiente | C12: Argumento de mercado | D12: Citarlo en la sustentación como evidencia de disposición a pagar | E12: Propuesto | F12: Sustentación
A13: Die Zeit | B13: Mercado sostenible de lectores que quieren profundidad | C13: Argumento de mercado | D13: Citarlo en la sustentación | E13: Propuesto | F13: Sustentación
A14: El Orden Mundial | B14: Mapas mentales y visualizaciones que facilitan comprensión; tono accesible; newsletter | C14: Visualizar el marco, no solo contarlo | D14: Infografía por pieza (en preparación) y un resumen visual del marco al final | E14: En preparación | F14: Infografías
A15: Daily Maverick | B15: Membresía (Maverick Insider) en el Sur Global para periodismo de profundidad | C15: Membresía como identidad | D15: Etiqueta visible "para miembros" cuando exista contenido de pago | E15: Por evaluar | F15: Monetización (línea 3)
... A24: Big Think (no está en tu tabla) | B24: Frase-promesa de una línea por columna; bajada de una línea por pieza; duración visible; números especiales; membresía y servicios para empresas | C24: Bajada clara y líneas temáticas con promesa propia | D24: Frase-promesa por línea temática en el home y filtro por línea desde el menú (hecho); bajada por pieza (ya tiene) | E24: Aplicado en parte | F24: Home

Sheet Cronograma
A1: Cronograma hasta la entrega y la sustentación
A2: Fechas propuestas a partir de tu cronograma (retesteo en octubre, KPIs y decisión en noviembre, entrega final a finales de noviembre o principios de diciembre, sustentación el 30 de enero de 2027). Lunes 12 de octubre es festivo. Ajusta según la disponibilidad real de tus sujetos.
A4: Fecha | B4: Día | C4: Foco | D4: Tareas | E4: Entregable | F4: Hipótesis / KPI | G4: Estado
A5: 2026-10-12 | B5: Lunes (festivo) | C5: Dejar todo listo | D5: Subir el index.html nuevo y verificar en el celular (foto circular, Foto1 y Foto2, FotoMagda3). Aplicar los 4 ajustes de GA4. Confirmar los 5 sujetos y horarios. Recortar el clip de la gobernadora (30 a 40 s) y subirlo. Etiquetar la versión del Chocó en GitHub. Desde hoy hasta el 16: solo correcciones de errores, ninguna función nueva. | E5: Versión congelada y publicada | F5: Validez del estudio | G5: Pendiente
A6: 2026-10-13 | B6: Martes | C6: Retesteo | D6: Sesiones 1 y 2, en el celular, con el mismo protocolo (P0 a P9, mismo orden) y el bloque B al final. Llenar la hoja Retesteo el mismo día. Claude entrega el bloque B y la encuesta. | E6: 2 filas del Excel; bloque B y encuesta redactados | F6: K1 a K9 | G6: Pendiente
A7: 2026-10-14 | B7: Miércoles | C7: Retesteo | D7: Sesiones 3 y 4. Registrar el minuto de la primera interrupción y si interactuaron con el modal. | E7: 2 filas más | F7: K1 a K9 | G7: Pendiente
A8: 2026-10-15 | B8: Jueves | C8: Retesteo y GA4 | D8: Sesión 5. Revisar en GA4 que llegan page_view y lectura_avance. Primer borrador del análisis. | E8: 5 filas completas; GA4 verificado | F8: K1 a K9 | G8: Pendiente
A9: 2026-10-16 | B9: Viernes | C9: Análisis | D9: Leer el semáforo del Excel, comparar con la línea de base y escribir la lectura de cada KPI. Actualizar el informe con datos reales. | E9: Informe de 2 páginas con datos del retesteo | F9: Decisión | G9: Pendiente
A10: 2026-10-17 | B10: Sábado | C10: Seguimiento y encuesta | D10: Mensaje personalizado a cada sujeto dentro de 48 horas de su sesión, con enlace a otra pieza y ?utm_source=mensaje&utm_campaign=h3. Abrir la encuesta post-lectura en tu red. | E10: Mensajes enviados; encuesta abierta | F10: H3 | G10: Pendiente
A11: 2026-10-18 | B11: Domingo | C11: Descanso | D11: Buffer para lo que se haya movido. | E11: — | F11: — | G11: Pendiente
A12: 2026-10-19 | B12: Semana 19 a 25 oct | C12: Iterar con lo aprendido | D12: Aplicar al Chocó y a las demás piezas lo que el retesteo muestre. Encender "continuar donde lo dejaste" y el segundo interactivo en el Chocó si el retesteo ya cerró. Enviar el newsletter piloto. Publicar y difundir por WhatsApp. | E12: Versión 2 del PMV; newsletter enviado | F12: H2, H3 | G12: Pendiente
A13: 2026-10-26 | B13: Semana 26 oct a 1 nov | C13: Monetización | D13: Preventa del taller con precio y lista de espera (mide intención real). Reunión con el profesor para confirmar la regla de decisión. Con los derechos aclarados, adaptar 1 pieza más. | E13: Preventa abierta; 4 piezas | F13: K7, K8 | G13: Pendiente
A14: 2026-11-02 | B14: Semana 2 a 8 nov | C14: Medición limpia | D14: Desde aquí el PMV queda congelado para medir. Cerrar la encuesta (30 respuestas o más) y analizarla. | E14: Informe de la encuesta | F14: K2, K7, K9 | G14: Pendiente
A15: 2026-11-09 | B15: Semana 9 a 15 nov | C15: Decisión | D15: Con 4 semanas de GA4, consolidar KPIs, fijar metas de analítica y completar la hoja Decisiones: continuar, ajustar o pivotar. Adaptar 1 pieza más si hay tiempo. | E15: Decisión documentada; 5 piezas | F15: Todos | G15: Pendiente
... A19: 2027-01-30 | B19: Sábado | C19: Sustentación | D19: Sustentación del proyecto. | E19: — | F19: — | G19: Pendiente
A22: Meta de contenido propuesta: 5 piezas con la arquitectura completa a fines de noviembre (las 3 actuales más 2 adaptaciones). Con 5 piezas el sitio de un solo archivo funciona bien: no migrar a una página por pieza hasta pasar de 6. Prioridad: evidencia antes que contenido.

Sheet Repositorio
A1: Lista de archivos del repositorio (trasfondo.github.io)
A2: Las carpetas y los nombres deben escribirse exactamente así (GitHub distingue mayúsculas). Si subes un archivo con el nombre exacto, la página lo muestra sola: no hay que tocar el HTML. Para cada foto se prueban también las extensiones .jpg, .jpeg, .png y .webp.
A4: Archivo | B4: Qué es | C4: Estado | D4: Formato y peso recomendado | E4: Dónde aparece
A5: index.html | B5: Sitio completo, con formulario de correos, índice de capítulos, Google Analytics, portadas, fotos y gráficos enlazados | C5: Subir ahora | D5: — | E5: Todas las pestañas
A6: og-card.png | B6: Imagen que aparece cuando se comparte el enlace | C6: Ya subido | D6: PNG 1200 × 630 | E6: Vista previa en WhatsApp y redes
A7: apple-touch-icon.png | B7: Ícono para la pantalla de inicio del iPhone | C7: Ya subido | D7: PNG 180 × 180 | E7: Pantalla de inicio
A8: favicon.svg y favicon-32.png | B8: Respaldo del ícono de la pestaña (el HTML ya lo trae embebido) | C8: Ya subido | D8: — | E8: Pestaña del navegador
A9: suscripciones.gs | B9: Código antiguo de suscripción, ya no se usa | C9: Borrar | D9: — | E9: —
A10: Multimedia HTML/Alejandrofirma.png | B10: Tu foto circular: firma de cada pieza (pequeña) y sección Quién (grande) | C10: Subido (verificar) | D10: PNG cuadrado con el rostro centrado; se recorta en círculo | E10: Firmas de las piezas y Quién
A11: Multimedia HTML/Fotos/Choco/FotoChoco0.jpeg | B11: Portada del Chocó (también el héroe del home). Pie: "Tras el vuelo del 14 de septiembre…" / Cortesía Satena | C11: Subido (verificar) | D11: JPEG, ancho 1600 px, hasta 300 KB. Se muestra en franja horizontal centrada | E11: Home y Chocó, antes de "Qué vas a entender"
A12: Multimedia HTML/Fotos/Choco/FotoChoco1.jpeg | B12: Alcalde y gobernadora | C12: Subido (verificar) | D12: JPEG | E12: Chocó, tras el párrafo "Hoy hay una primera oferta…"
A13: Multimedia HTML/Fotos/Choco/FotoChoco2.jpeg | B13: Avión descargado por voluntarios | C13: Subido (verificar) | D13: JPEG | E13: Chocó, tras "—No estamos quietos."
A14: Multimedia HTML/Fotos/Aviturismo/Foto0.jpg | B14: Portada del aviturismo (colibrí pechirrojo). Crédito: Jorge Muñoz, en @caquetabirding | C14: Subido (verificar) | D14: JPG | E14: Aviturismo (antes de "Qué vas a entender") y tarjeta del home
A15: Multimedia HTML/Fotos/Aviturismo/Foto1.jpg | B15: Portada de la ruta de Jeanne (dacnis turquesa). Crédito: Jorge Muñoz, en @caquetabirding. No cargaba en la prueba | C15: Subido (verificar) | D15: JPG | E15: Ruta "Con binoculares y pasión", antes del primer párrafo
... A27: audio/magda.mp3 | B27: Audio de apertura del perfil de Magda | C27: Pendiente de ti | D27: MP3 mono 64 a 96 kbps | E27: Magda, después de "Qué vas a entender"
A29: Para ver los marcadores de lo que falta, abre la página con ?edicion=1 al final del enlace (https://trasfondo.github.io/?edicion=1). En el modo normal, lo que no existe no se muestra.
